<?xml version="1.0" encoding="utf-8"?>
<widget id="wengao.addressfinder.AddressFinder" pluginWidget="true" needsEntityContext="true" offlineCapable="true" supportedPlatform="Web"
    xmlns="http://www.mendix.com/widget/1.0/"
    xmlns:xsi="http://www.w3.org/2001/XMLSchema-instance" xsi:schemaLocation="http://www.mendix.com/widget/1.0/ ../node_modules/mendix/custom_widget.xsd">
    <name>Address Finder</name>
    <description>My widget description</description>
    <icon/>
    <properties>
        <propertyGroup caption="General">
            <property key="fullAddress" type="attribute" required="false">
                <caption>Full Address</caption>
                <description></description>
                <attributeTypes>
                    <attributeType name="String"/>
                </attributeTypes>
            </property>

            <property key="line1" type="attribute" required="false">
                <caption>Line 1</caption>
                <description></description>
                <attributeTypes>
                    <attributeType name="String"/>
                </attributeTypes>
            </property>
            <property key="line2" type="attribute" required="false">
                <caption>Line 2</caption>
                <description></description>
                <attributeTypes>
                    <attributeType name="String"/>
                </attributeTypes>
            </property>
            <property key="suburb" type="attribute" required="false">
                <caption>Suburb</caption>
                <description></description>
                <attributeTypes>
                    <attributeType name="String"/>
                </attributeTypes>
            </property>
            <property key="state" type="attribute" required="false">
                <caption>State</caption>
                <description></description>
                <attributeTypes>
                    <attributeType name="String"/>
                </attributeTypes>
            </property>
            <property key="postcode" type="attribute" required="false">
                <caption>Postcode</caption>
                <description></description>
                <attributeTypes>
                    <attributeType name="String"/>
                </attributeTypes>
            </property>
            <property key="country" type="attribute" required="false">
                <caption>Country</caption>
                <description></description>
                <attributeTypes>
                    <attributeType name="String"/>
                </attributeTypes>
            </property>
            <property key="city" type="attribute" required="false">
                <caption>City</caption>
                <description></description>
                <attributeTypes>
                    <attributeType name="String"/>
                </attributeTypes>
            </property>
        </propertyGroup>
        <propertyGroup caption="Options">
            <!-- https://docs.mendix.com/apidocs-mxsdk/apidocs/pluggable-widgets-property-types/#413-studio-pro-ui -->
            <property key="apiKey" type="textTemplate">
                <caption>API Key</caption>
                <description>API Key for the Address Finder API</description>
            </property>
        </propertyGroup>
    </properties>
</widget>